acme_client/__init__.py
acme_client/api_client.py
acme_client/api_response.py
acme_client/apis/__init__.py
acme_client/apis/path_to_api.py
acme_client/apis/paths/__init__.py
acme_client/apis/paths/pagination.py
acme_client/apis/paths/pet.py
acme_client/apis/paths/pet_find_by_status.py
acme_client/apis/paths/pet_find_by_tags.py
acme_client/apis/paths/pet_pet_id.py
acme_client/apis/paths/pet_pet_id_upload_image.py
acme_client/apis/paths/store_inventory.py
acme_client/apis/paths/store_order.py
acme_client/apis/paths/store_order_order_id.py
acme_client/apis/paths/user.py
acme_client/apis/paths/user_create_with_array.py
acme_client/apis/paths/user_create_with_list.py
acme_client/apis/paths/user_login.py
acme_client/apis/paths/user_logout.py
acme_client/apis/paths/user_username.py
acme_client/apis/tag_to_api.py
acme_client/apis/tags/__init__.py
acme_client/apis/tags/miscellaneous_api.py
acme_client/apis/tags/pet_api.py
acme_client/apis/tags/store_api.py
acme_client/apis/tags/user_api.py
acme_client/client.py
acme_client/client.pyi
acme_client/client_custom.py
acme_client/configuration.py
acme_client/exceptions.py
acme_client/exceptions_base.py
acme_client/model/__init__.py
acme_client/model/api_response.py
acme_client/model/api_response.pyi
acme_client/model/category.py
acme_client/model/category.pyi
acme_client/model/create_with_array_request.py
acme_client/model/create_with_array_request.pyi
acme_client/model/find_by_status200_response.py
acme_client/model/find_by_status200_response.pyi
acme_client/model/find_by_status_response.py
acme_client/model/find_by_status_response.pyi
acme_client/model/find_by_tags200_response.py
acme_client/model/find_by_tags200_response.pyi
acme_client/model/find_by_tags_response.py
acme_client/model/find_by_tags_response.pyi
acme_client/model/get_inventory_response.py
acme_client/model/get_inventory_response.pyi
acme_client/model/login200_response.py
acme_client/model/login200_response.pyi
acme_client/model/login_response.py
acme_python_sdk-1.0.0.dist-info/LICENSE
acme_python_sdk-1.0.0.dist-info/METADATA
acme_python_sdk-1.0.0.dist-info/WHEEL
acme_python_sdk-1.0.0.dist-info/RECORD
